rustfrecord-0.1.7.dist-info/METADATA
rustfrecord-0.1.7.dist-info/WHEEL
rustfrecord/__init__.py
rustfrecord/rustfrecord.abi3.so
rustfrecord-0.1.7.dist-info/RECORD
