Metadata-Version: 2.3
Name: rustfrecord
Version: 0.1.7
Classifier: Programming Language :: Rust
Classifier: Programming Language :: Python :: Implementation :: CPython
Requires-Dist: setuptools ==69.5.1
Requires-Dist: torch ==2.2.0
Requires-Dist: maturin ==1.5.1
Requires-Dist: pip ==24.0
Requires-Dist: numpy ==1.24.4
Summary: Rust implementation to read TFRecord files into PyTorch tensors
Requires-Python: >=3.8
